Workbook

Sheet Inventory
A1: 📷 DIGICAM VENTURE — INVENTORY TRACKER
A2: Camera ID | B2: Brand | C2: Model | D2: Year | E2: Condition | F2: Asking Price (S$) | G2: Cost Price (S$) | H2: Units In Stock | I2: Units Sold | J2: Reorder Level | K2: Status | L2: Listed on TG | M2: Listed on Web | N2: Last Updated | O2: Notes
A3: CAM-001 | B3: Canon | C3: PowerShot G7X Mark III | D3: 2019 | E3: Excellent | F3: 420 | G3: 280 | H3: 2 | I3: 0 | J3: 1 | K3: In Stock | L3: YES | M3: YES | N3: =TODAY() -> 46134
A4: CAM-002 | B4: Sony | C4: Cyber-shot DSC-RX100 VII | D4: 2019 | E4: Good | F4: 550 | G4: 380 | H4: 1 | I4: 0 | J4: 1 | K4: Low Stock | L4: YES | M4: YES | N4: =TODAY() -> 46134
A5: CAM-003 | B5: Ricoh | C5: GR IIIx | D5: 2021 | E5: Excellent | F5: 780 | G5: 560 | H5: 3 | I5: 1 | J5: 2 | K5: In Stock | L5: YES | M5: YES | N5: =TODAY() -> 46134
A6: CAM-004 | B6: Fuji | C6: X100V | D6: 2020 | E6: Like New | F6: 1050 | G6: 800 | H6: 1 | I6: 0 | J6: 1 | K6: Low Stock | L6: YES | M6: YES | N6: =TODAY() -> 46134
A7: CAM-005 | B7: Nikon | C7: Coolpix A1000 | D7: 2019 | E7: Good | F7: 180 | G7: 100 | H7: 4 | I7: 2 | J7: 2 | K7: In Stock | L7: YES | M7: YES | N7: =TODAY() -> 46134
A8: CAM-006 | B8: Olympus | C8: TG-6 | D8: 2019 | E8: Excellent | F8: 280 | G8: 170 | H8: 0 | I8: 3 | J8: 1 | K8: Sold Out | L8: NO | M8: NO | N8: =TODAY() -> 46134
A9: CAM-007 | B9: Olympus | C9: TG-7 | D9: 2020 | E9: Excellent | F9: 280 | G9: 170 | H9: 0 | I9: 3 | J9: 1 | K9: Sold Out | L9: NO | M9: NO | N9: =TODAY() -> 46134
A10: CAM-008 | B10: Olympus | C10: TG-8 | D10: 2021 | E10: Excellent | F10: 280 | G10: 170 | H10: 0 | I10: 3 | J10: 1 | K10: Sold Out | L10: NO | M10: NO | N10: =TODAY() -> 46134
A11: CAM-009 | B11: Olympus | C11: TG-9 | D11: 2022 | E11: Excellent | F11: 280 | G11: 170 | H11: 0 | I11: 3 | J11: 1 | K11: Sold Out | L11: NO | M11: NO | N11: =TODAY() -> 46134
A12: CAM-010 | B12: Olympus | C12: TG-10 | D12: 2023 | E12: Excellent | F12: 280 | G12: 170 | H12: 0 | I12: 3 | J12: 1 | K12: Sold Out | L12: NO | M12: NO | N12: =TODAY() -> 46134
A13: CAM-011 | B13: Olympus | C13: TG-11 | D13: 2024 | E13: Excellent | F13: 280 | G13: 170 | H13: 0 | I13: 3 | J13: 1 | K13: Sold Out | L13: NO | M13: NO | N13: =TODAY() -> 46134
A14: CAM-012 | B14: Olympus | C14: TG-12 | D14: 2025 | E14: Excellent | F14: 280 | G14: 170 | H14: 0 | I14: 3 | J14: 1 | K14: Sold Out | L14: NO | M14: NO | N14: =TODAY() -> 46134
... A16: CAM-014 | B16: Olympus | C16: TG-14 | D16: 2027 | E16: Excellent | F16: 280 | G16: 170 | H16: 0 | I16: 3 | J16: 1 | K16: Sold Out | L16: NO | M16: NO | N16: =TODAY() -> 46134

Sheet Sales Log
A1: 📋 SALES LOG
A2: Sale ID | B2: Date | C2: Camera ID | D2: Brand | E2: Model | F2: Sale Price (S$) | G2: Channel | H2: Buyer Contact | I2: Payment | J2: Notes
A3: SALE-001 | B3: 2025-01-15 | C3: CAM-003 | D3: Ricoh | E3: GR IIIx | F3: 780 | G3: Telegram | H3: @buyer123 | I3: PayNow

Sheet Dashboard
A1: 📊 DASHBOARD
A3: Total Models Listed | B3: =COUNTA(Inventory!C3:C50)-COUNTIF(Inventory!C3:C50,"") -> -20
A4: Total Units In Stock | B4: =SUM(Inventory!H3:H50) -> 11
A5: Total Units Sold | B5: =SUM(Inventory!I3:I50) -> 30
A6: Models: In Stock | B6: =COUNTIF(Inventory!K3:K50,"In Stock") -> 3
A7: Models: Low Stock | B7: =COUNTIF(Inventory!K3:K50,"Low Stock") -> 2
A8: Models: Sold Out | B8: =COUNTIF(Inventory!K3:K50,"Sold Out") -> 9
A9: Total Revenue (S$) | B9: =SUMPRODUCT((Inventory!I3:I50)*(Inventory!F3:F50)) -> 8700
A11: ⚠️ Cameras to Reorder
A12: Camera ID | B12: Brand | C12: Model | D12: In Stock | E12: Reorder Level | F12: Status
A14: ↑ Rows with Low Stock or Sold Out status from Inventory sheet appear here (filter manually or via automation)
